Workbook

Sheet How to use
A1: Feature priorities — Gardening Companion
A3: 1. Open the "Priorities" sheet.
A4: 2. In the yellow "Your priority" column, pick one value for each row:
A5: • MVP — needed in the first usable version
A6: • Good to have — after the MVP, still planned
A7: • Future improvement — later, maybe
A8: 3. "Suggested" is Claude's suggestion, for reference only. Change anything.
A9: 4. Use "Your notes" for comments or changes to a row.
A10: 5. Only edit the yellow columns. The "Summary" sheet counts your choices automatically.
A11: 6. Rows marked "Decided earlier: not in MVP" were already agreed as later — change them if you've changed your mind.
A12: 7. When finished, export as Excel (Share → Export → Excel) and send the file back in the chat.
A14: Example: row "Plot boundary on satellite map" → Your priority: MVP → Your notes: "Tap corners is enough"

Sheet Priorities
A1: ID | B1: Feature | C1: Sub-feature | D1: What it means | E1: Your priority | F1: Suggested | G1: Your notes | H1: Info
A2: 0.1 | B2: Foundations | C2: Sign-in and accounts | D2: Entra External ID sign-in (email, Apple, Google); every record belongs to a user | F2: MVP | H2: Needed by almost everything
A3: 0.2 | B3: Foundations | C3: Portuguese and English | D3: Whole app and content in pt-PT and English | F3: MVP | H3: Decided earlier: first version
A4: 0.3 | B4: Foundations | C4: Offline sync | D4: Work offline and sync later; you resolve conflicts yourself | F4: MVP | H4: Needed by journal, tasks, map
A5: 0.4 | B5: Foundations | C5: Activity log | D5: Permanent history of everything done; base for roadmap, journal and AI | F5: MVP | H5: Needed by roadmap, journal and AI
A6: 0.5 | B6: Foundations | C6: Knowledge base pipeline | D6: Crops, guides and tools kept in git (PT/EN), published to the app and AI | F6: MVP | H6: Needed by calendar, guides and AI
A7: 0.6 | B7: Foundations | C7: Account deletion and data export | D7: Required by Apple and Google for apps with accounts | F7: MVP | H7: Store requirement
A8: 0.7 | B8: Foundations | C8: Android app | D8: Port each stable iOS milestone to Android | F8: Good to have | H8: Decided earlier: iOS first
A9: 3.1.1 | B9: Project roadmap | C9: Next actions (rules) | D9: Fixed agronomy rules work out the next actions per zone, with safety limits | F9: MVP
A10: 3.1.2 | B10: Project roadmap | C10: Next actions (AI) | D10: AI ranks and adapts next actions, explains why | F10: Good to have
A11: 3.1.3 | B11: Project roadmap | C11: Per-zone stages | D11: Each zone has its own stage, worked out from its state | F11: MVP
A12: 3.1.4 | B12: Project roadmap | C12: Starting point | D12: Setup asks what already exists so you don't start from zero | F12: MVP
A13: 3.1.5 | B13: Project roadmap | C13: Season-aware timing | D13: Actions scheduled in their ideal time window for your climate | F13: MVP
A14: 3.1.6 | B14: Project roadmap | C14: Time and cost estimates | D14: Rough time and cost for each action | F14: Good to have
A15: 3.1.7 | B15: Project roadmap | C15: Deviation handling | D15: Mark actions as done differently, skipped, not possible or a problem; plan adapts | F15: MVP
A16: 3.1.8 | B16: Project roadmap | C16: Content freshness review | D16: AI proposes updates to outdated content; you review before publishing | F16: Future improvement
A17: 3.3.1 | B17: Plot mapping | C17: Plot boundary on satellite map | D17: Draw the plot by tapping corners | F17: MVP
A18: 3.3.2 | B18: Plot mapping | C18: Walk boundary with GPS | D18: Walk around the plot to draw it | F18: Good to have
A19: 3.3.3 | B19: Plot mapping | C19: Zones and beds | D19: Draw zones and beds, or enter exact dimensions | F19: MVP
A20: 3.3.4 | B20: Plot mapping | C20: Points of interest | D20: Water, electricity, access, buildings, trees with heights | F20: MVP | H20: Irrigation needs water sources
A21: 3.3.5 | B21: Plot mapping | C21: Area, sun and slope | D21: Calculated automatically from the map and elevation data | F21: MVP
A22: 3.3.6 | B22: Plot mapping | C22: Soil type estimate | D22: Estimated from global soil maps (SoilGrids), no tests | F22: Good to have
A23: 3.3.7 | B23: Plot mapping | C23: Shade estimation | D23: Shade from trees and buildings over the day and year, plus observed shade | F23: Good to have
A24: 3.3.8 | B24: Plot mapping | C24: Prevailing wind | D24: Wind direction from weather data, windbreak suggestions | F24: Future improvement
A25: 3.3.9 | B25: Plot mapping | C25: Layout designer | D25: Beds with real dimensions, paths, row direction | F25: MVP
A26: 3.3.10 | B26: Plot mapping | C26: Measuring tool | D26: Measure distances on the map (e.g. pipe length) | F26: Good to have
A27: 3.3.11 | B27: Plot mapping | C27: Layout history | D27: Each season's layout kept as a version | F27: Good to have | H27: Rotation planner needs it
A28: 3.3.12 | B28: Plot mapping | C28: Several plots per user | D28: e.g. a backyard and a separate field | F28: Future improvement | H28: Decided earlier: not in MVP
A29: 3.4.1 | B29: Site assessment | C29: AI photo assessment | D29: Vegetation to clear, problem plants, trees to keep, obstacles, terrain, water problems, infrastructure | F29: MVP
A30: 3.4.2 | B30: Site assessment | C30: Wildlife pressure | D30: Signs of rabbits, wild boar, birds, moles; fencing advice | F30: Good to have
A31: 3.4.3 | B31: Site assessment | C31: Fixed photo spots | D31: Guided photos from the same spots for before-and-after | F31: Good to have
A32: 3.4.4 | B32: Site assessment | C32: Walk-around video | D32: Film a zone; the app picks frames for the AI | F32: Future improvement
A33: 3.4.5 | B33: Site assessment | C33: Equipment advice | D33: Buy, rent or borrow big equipment (follows "always own") | F33: Good to have
A34: 3.4.6 | B34: Site assessment | C34: Re-assessments | D34: Repeat the assessment to track progress | F34: Good to have
A35: 3.5.1 | B35: Planting calendar | C35: Climate-based windows | D35: Sow, plant-out and harvest windows from local climate history | F35: MVP
A36: 3.5.2 | B36: Planting calendar | C36: Too-hot windows | D36: Avoid heat for crops that bolt or stop fruiting | F36: MVP | H36: Critical in Alentejo
A37: 3.5.3 | B37: Planting calendar | C37: Month view and "This week" | D37: Calendar views | F37: MVP
A38: 3.5.4 | B38: Planting calendar | C38: Forecast adjustment | D38: Windows shifted by the weather forecast | F38: Good to have
A39: 3.5.5 | B39: Planting calendar | C39: Zone fit | D39: What can be planted now in each zone (sun and shade) | F39: Good to have
A40: 3.5.6 | B40: Planting calendar | C40: Varieties | D40: Early and late varieties with different timing | F40: Good to have
A41: 3.5.7 | B41: Planting calendar | C41: Day length | D41: Varieties suited to your latitude (e.g. short-day onions) | F41: Good to have
A42: 3.5.8 | B42: Planting calendar | C42: Heat-based harvest estimates | D42: Harvest dates from heat received since sowing | F42: Good to have
A43: 3.5.9 | B43: Planting calendar | C43: Staggered sowing reminders | D43: e.g. lettuce every 2–3 weeks | F43: Good to have
A44: 3.5.10 | B44: Planting calendar | C44: Export to phone calendar | D44: Add sowing and harvest dates to iOS Calendar | F44: Future improvement
A45: 3.6.1 | B45: Choosing your crops | C45: Pick crops | D45: Choose crops with variety, priority and quantity | F45: MVP
A46: 3.6.2 | B46: Choosing your crops | C46: Ranked suggestions | D46: Crops ranked by fit for your location, with reasons | F46: MVP
A47: 3.6.3 | B47: Choosing your crops | C47: Poor-fit warnings | D47: Warns about a bad crop or timing, never blocks | F47: MVP
A48: 3.6.4 | B48: Choosing your crops | C48: How much to plant | D48: Number of plants and space from the quantity you want | F48: Good to have
... A62: 3.7.13 | B62: Guides | C62: AI illustrations | D62: gpt-image illustrations plus diagrams, reviewed by you | F62: Good to have
A63: 3.7.14 | B63: Guides | C63: AI-generated video or animations | D63: Generated once per guide and reviewed | F63: Future improvement | H63: Decided earlier: not in MVP
A64: 3.8.1 | B64: Journal and timeline | C64: Entries with photos and notes | D64: Log what you did per zone, bed or planting | F64: MVP
A65: 3.8.2 | B65: Journal and timeline | C65: Quick and bulk logging | D65: One tap; several beds at once | F65: MVP
A66: 3.8.3 | B66: Journal and timeline | C66: Voice notes | D66: Dictate notes in the field | F66: Good to have
A67: 3.8.4 | B67: Journal and timeline | C67: Automatic entries | D67: Completing actions, tasks or guide steps logs them | F67: MVP
A68: 3.8.5 | B68: Journal and timeline | C68: Weather on each day | D68: Day's rain and temperatures attached automatically | F68: Good to have
A69: 3.8.6 | B69: Journal and timeline | C69: Change the date | D69: Log things after the fact | F69: MVP
A70: 3.8.7 | B70: Journal and timeline | C70: Timeline views | D70: History for a zone, bed or planting | F70: Good to have
A71: 3.8.8 | B71: Journal and timeline | C71: Photo time-lapse | D71: From the fixed photo spots | F71: Future improvement
A72: 3.8.9 | B72: Journal and timeline | C72: Harvest log | D72: Weight or count per crop, compared with expected | F72: MVP
A73: 3.8.10 | B73: Journal and timeline | C73: Harvest value | D73: Estimated value using prices you enter | F73: Future improvement
A74: 3.8.11 | B74: Journal and timeline | C74: Search and filters | D74: Find past entries | F74: Good to have
A75: 3.8.12 | B75: Journal and timeline | C75: Export CSV/PDF | D75: Export your journal | F75: Future improvement
... A87: 3.9.12 | B87: Tasks and reminders | C87: Quiet hours | D87: No notifications at set times | F87: Good to have
A88: 3.9.13 | B88: Tasks and reminders | C88: Share tasks with family | D88: Helpers see and do tasks | F88: Future improvement | H88: Decided earlier: not in MVP
A89: 3.10.1 | B89: Tools | C89: My tools with reference images | D89: List of owned tools, each with an image to recognise it | F89: MVP
A90: 3.10.2 | B90: Tools | C90: Own photo of a tool | D90: Replace the reference image with your photo | F90: Future improvement
A91: 3.10.3 | B91: Tools | C91: Tools needed per action | D91: Actions, tasks and guides list their tools | F91: MVP
A92: 3.10.4 | B92: Tools | C92: "Tools to get" list | D92: Missing tools ordered by when needed | F92: MVP
A93: 3.10.5 | B93: Tools | C93: "Always own" setting | D93: Default to buy; hide rent and borrow | F93: MVP | H93: You use this setting
A94: 3.10.6 | B94: Tools | C94: Starter toolkit | D94: Recommended set for your plot: essential vs nice to have | F94: MVP
A95: 3.10.7 | B95: Tools | C95: Buy/rent/borrow advice | D95: For big equipment (hidden when "always own" is on) | F95: Future improvement
A96: 3.10.8 | B96: Tools | C96: Maintenance reminders | D96: Sharpen, clean, store before frost | F96: Good to have
A97: 3.10.9 | B97: Tools | C97: Shop links and affiliates | D97: Commercial idea | F97: Future improvement | H97: Decided earlier: not in MVP
A98: 3.11.1 | B98: Irrigation planner | C98: Water sources and bucket test | D98: Sources from the map; measure flow rate | F98: MVP
A99: 3.11.2 | B99: Irrigation planner | C99: Method per bed | D99: Drip line, drippers, soaker hose or sprinklers | F99: MVP
A100: 3.11.3 | B100: Irrigation planner | C100: System layout on map | D100: Main pipe, branches, drip lines per bed | F100: MVP
A101: 3.11.4 | B101: Irrigation planner | C101: Flow check and sectors | D101: Split into sectors if flow is too low; filter, regulator, backflow | F101: MVP
A102: 3.11.5 | B102: Irrigation planner | C102: Parts list | D102: For information only | F102: MVP
A103: 3.11.6 | B103: Irrigation planner | C103: Watering schedule | D103: Run times from crop and season guidance, adjusted by weather; creates tasks | F103: MVP
A104: 3.11.7 | B104: Irrigation planner | C104: Hand-watering guidance | D104: Before a system is installed | F104: MVP
A105: 3.11.8 | B105: Irrigation planner | C105: Mulching advice | D105: Reduce water use | F105: Good to have
A106: 3.11.9 | B106: Irrigation planner | C106: Rainwater harvesting estimate | D106: Roof area × rainfall, tank size | F106: Future improvement
A107: 3.11.10 | B107: Irrigation planner | C107: Seasonal reminders | D107: Flush lines, clean filters, drain before frost | F107: Good to have
A108: 3.11.11 | B108: Irrigation planner | C108: Smart controllers and sensors | D108: Connect irrigation controllers and soil moisture sensors | F108: Future improvement | H108: Decided earlier: not in MVP
A109: 3.12.1 | B109: Weather alerts | C109: Crop-aware alerts | D109: Frost, heat, wind, rain, hail, storms, dry spells — only when your crops are at risk | F109: MVP
A110: 3.12.2 | B110: Weather alerts | C110: Skip-watering notices | D110: Rain is coming | F110: MVP
A111: 3.12.3 | B111: Weather alerts | C111: Good-conditions alerts | D111: e.g. good day to plant out | F111: Good to have
A112: 3.12.4 | B112: Weather alerts | C112: Actions as tasks | D112: Each alert creates tasks with guide links | F112: MVP
A113: 3.12.5 | B113: Weather alerts | C113: Severity and confidence | D113: Watch vs warning; forecast confidence | F113: Good to have
A114: 3.12.6 | B114: Weather alerts | C114: Quiet-hours override | D114: Urgent alerts break through quiet hours | F114: Good to have
A115: 3.12.7 | B115: Weather alerts | C115: 7-day weather screen | D115: Forecast with gardening notes | F115: MVP
A116: 3.12.8 | B116: Weather alerts | C116: Follow-up after event | D116: Check plants and log damage after frost or storm | F116: Good to have
A117: 3.12.9 | B117: Weather alerts | C117: IPMA official warnings | D117: Portuguese official weather warnings | F117: Good to have
A118: 3.12.10 | B118: Weather alerts | C118: Other countries' warnings | D118: MeteoAlarm or national services | F118: Future improvement | H118: Decided earlier: not in MVP
A119: 3.13.1 | B119: Plant identification | C119: Photo identification | D119: Top matches with confidence, PT/EN and scientific names | F119: MVP
A120: 3.13.2 | B120: Plant identification | C120: Crop-or-weed verdict | D120: Especially for seedlings | F120: MVP
A121: 3.13.3 | B121: Plant identification | C121: Context for accuracy | D121: Uses location, season and what's planted in the bed | F121: MVP
A122: 3.13.4 | B122: Plant identification | C122: Several photos | D122: Leaf, flower, whole plant | F122: Good to have
A123: 3.13.5 | B123: Plant identification | C123: Invasive and toxic flags | D123: Warnings only; never says a wild plant is safe to eat | F123: MVP
A124: 3.13.6 | B124: Plant identification | C124: One-tap actions | D124: Add as planting, mark as weed (removal task), keep tree | F124: Good to have
...

Sheet Summary
A1: Feature | B1: MVP | C1: Good to have | D1: Future improvement | E1: Not decided | F1: Total
A2: Foundations | B2: =COUNTIFS(Priorities!$B$2:$B$186,$A2,Priorities!$E$2:$E$186,"MVP") -> 0 | C2: =COUNTIFS(Priorities!$B$2:$B$186,$A2,Priorities!$E$2:$E$186,"Good to have") -> 0 | D2: =COUNTIFS(Priorities!$B$2:$B$186,$A2,Priorities!$E$2:$E$186,"Future improvement") -> 0 | E2: =F2-B2-C2-D2 -> 7 | F2: =COUNTIF(Priorities!$B$2:$B$186,$A2) -> 7
A3: Project roadmap | B3: =COUNTIFS(Priorities!$B$2:$B$186,$A3,Priorities!$E$2:$E$186,"MVP") -> 0 | C3: =COUNTIFS(Priorities!$B$2:$B$186,$A3,Priorities!$E$2:$E$186,"Good to have") -> 0 | D3: =COUNTIFS(Priorities!$B$2:$B$186,$A3,Priorities!$E$2:$E$186,"Future improvement") -> 0 | E3: =F3-B3-C3-D3 -> 8 | F3: =COUNTIF(Priorities!$B$2:$B$186,$A3) -> 8
A4: Plot mapping | B4: =COUNTIFS(Priorities!$B$2:$B$186,$A4,Priorities!$E$2:$E$186,"MVP") -> 0 | C4: =COUNTIFS(Priorities!$B$2:$B$186,$A4,Priorities!$E$2:$E$186,"Good to have") -> 0 | D4: =COUNTIFS(Priorities!$B$2:$B$186,$A4,Priorities!$E$2:$E$186,"Future improvement") -> 0 | E4: =F4-B4-C4-D4 -> 12 | F4: =COUNTIF(Priorities!$B$2:$B$186,$A4) -> 12
A5: Site assessment | B5: =COUNTIFS(Priorities!$B$2:$B$186,$A5,Priorities!$E$2:$E$186,"MVP") -> 0 | C5: =COUNTIFS(Priorities!$B$2:$B$186,$A5,Priorities!$E$2:$E$186,"Good to have") -> 0 | D5: =COUNTIFS(Priorities!$B$2:$B$186,$A5,Priorities!$E$2:$E$186,"Future improvement") -> 0 | E5: =F5-B5-C5-D5 -> 6 | F5: =COUNTIF(Priorities!$B$2:$B$186,$A5) -> 6
A6: Planting calendar | B6: =COUNTIFS(Priorities!$B$2:$B$186,$A6,Priorities!$E$2:$E$186,"MVP") -> 0 | C6: =COUNTIFS(Priorities!$B$2:$B$186,$A6,Priorities!$E$2:$E$186,"Good to have") -> 0 | D6: =COUNTIFS(Priorities!$B$2:$B$186,$A6,Priorities!$E$2:$E$186,"Future improvement") -> 0 | E6: =F6-B6-C6-D6 -> 10 | F6: =COUNTIF(Priorities!$B$2:$B$186,$A6) -> 10
A7: Choosing your crops | B7: =COUNTIFS(Priorities!$B$2:$B$186,$A7,Priorities!$E$2:$E$186,"MVP") -> 0 | C7: =COUNTIFS(Priorities!$B$2:$B$186,$A7,Priorities!$E$2:$E$186,"Good to have") -> 0 | D7: =COUNTIFS(Priorities!$B$2:$B$186,$A7,Priorities!$E$2:$E$186,"Future improvement") -> 0 | E7: =F7-B7-C7-D7 -> 5 | F7: =COUNTIF(Priorities!$B$2:$B$186,$A7) -> 5
A8: Guides | B8: =COUNTIFS(Priorities!$B$2:$B$186,$A8,Priorities!$E$2:$E$186,"MVP") -> 0 | C8: =COUNTIFS(Priorities!$B$2:$B$186,$A8,Priorities!$E$2:$E$186,"Good to have") -> 0 | D8: =COUNTIFS(Priorities!$B$2:$B$186,$A8,Priorities!$E$2:$E$186,"Future improvement") -> 0 | E8: =F8-B8-C8-D8 -> 14 | F8: =COUNTIF(Priorities!$B$2:$B$186,$A8) -> 14
A9: Journal and timeline | B9: =COUNTIFS(Priorities!$B$2:$B$186,$A9,Priorities!$E$2:$E$186,"MVP") -> 0 | C9: =COUNTIFS(Priorities!$B$2:$B$186,$A9,Priorities!$E$2:$E$186,"Good to have") -> 0 | D9: =COUNTIFS(Priorities!$B$2:$B$186,$A9,Priorities!$E$2:$E$186,"Future improvement") -> 0 | E9: =F9-B9-C9-D9 -> 12 | F9: =COUNTIF(Priorities!$B$2:$B$186,$A9) -> 12
A10: Tasks and reminders | B10: =COUNTIFS(Priorities!$B$2:$B$186,$A10,Priorities!$E$2:$E$186,"MVP") -> 0 | C10: =COUNTIFS(Priorities!$B$2:$B$186,$A10,Priorities!$E$2:$E$186,"Good to have") -> 0 | D10: =COUNTIFS(Priorities!$B$2:$B$186,$A10,Priorities!$E$2:$E$186,"Future improvement") -> 0 | E10: =F10-B10-C10-D10 -> 13 | F10: =COUNTIF(Priorities!$B$2:$B$186,$A10) -> 13
A11: Tools | B11: =COUNTIFS(Priorities!$B$2:$B$186,$A11,Priorities!$E$2:$E$186,"MVP") -> 0 | C11: =COUNTIFS(Priorities!$B$2:$B$186,$A11,Priorities!$E$2:$E$186,"Good to have") -> 0 | D11: =COUNTIFS(Priorities!$B$2:$B$186,$A11,Priorities!$E$2:$E$186,"Future improvement") -> 0 | E11: =F11-B11-C11-D11 -> 9 | F11: =COUNTIF(Priorities!$B$2:$B$186,$A11) -> 9
A12: Irrigation planner | B12: =COUNTIFS(Priorities!$B$2:$B$186,$A12,Priorities!$E$2:$E$186,"MVP") -> 0 | C12: =COUNTIFS(Priorities!$B$2:$B$186,$A12,Priorities!$E$2:$E$186,"Good to have") -> 0 | D12: =COUNTIFS(Priorities!$B$2:$B$186,$A12,Priorities!$E$2:$E$186,"Future improvement") -> 0 | E12: =F12-B12-C12-D12 -> 11 | F12: =COUNTIF(Priorities!$B$2:$B$186,$A12) -> 11
A13: Weather alerts | B13: =COUNTIFS(Priorities!$B$2:$B$186,$A13,Priorities!$E$2:$E$186,"MVP") -> 0 | C13: =COUNTIFS(Priorities!$B$2:$B$186,$A13,Priorities!$E$2:$E$186,"Good to have") -> 0 | D13: =COUNTIFS(Priorities!$B$2:$B$186,$A13,Priorities!$E$2:$E$186,"Future improvement") -> 0 | E13: =F13-B13-C13-D13 -> 10 | F13: =COUNTIF(Priorities!$B$2:$B$186,$A13) -> 10
... A21: Commercial readiness | B21: =COUNTIFS(Priorities!$B$2:$B$186,$A21,Priorities!$E$2:$E$186,"MVP") -> 0 | C21: =COUNTIFS(Priorities!$B$2:$B$186,$A21,Priorities!$E$2:$E$186,"Good to have") -> 0 | D21: =COUNTIFS(Priorities!$B$2:$B$186,$A21,Priorities!$E$2:$E$186,"Future improvement") -> 0 | E21: =F21-B21-C21-D21 -> 5 | F21: =COUNTIF(Priorities!$B$2:$B$186,$A21) -> 5
A22: Total | B22: =SUM(B2:B21) -> 0 | C22: =SUM(C2:C21) -> 0 | D22: =SUM(D2:D21) -> 0 | E22: =SUM(E2:E21) -> 185 | F22: =SUM(F2:F21) -> 185
